lumei/__init__.py
lumei/__main__.py
lumei/attribute_processor.py
lumei/cli.py
lumei/command_processor.py
lumei/execution_scheduler.py
lumei/file_manager.py
lumei/query_executor.py
lumei/query_param.py
lumei/openai/__init__.py
lumei/openai/agent.py
lumei/openai/file_search.py
lumei/openai/standalone_file_search.py
lumei-0.6.0.dist-info/LICENSE
lumei-0.6.0.dist-info/METADATA
lumei-0.6.0.dist-info/WHEEL
lumei-0.6.0.dist-info/entry_points.txt
lumei-0.6.0.dist-info/top_level.txt
lumei-0.6.0.dist-info/RECORD
