Metadata-Version: 2.1
Name: lumei
Version: 0.6.0
Summary: File search tool using OpenAI assistant.
Author-email: David Zhang <dev@hansololz.com>
License: GNU GENERAL PUBLIC LICENSE
Requires-Python: >=3.12
License-File: LICENSE
Requires-Dist: openai==1.42.0
Requires-Dist: pandas==2.2.2
Requires-Dist: absl-py==2.1.0
Requires-Dist: openpyxl==3.1.5
Requires-Dist: prettytable==3.11.0
